{
  "country_iso3": "RUS",
  "world_bank": {
    "indicators": [
      {
        "id": "SP.POP.TOTL",
        "name": "Population, total"
      },
      {
        "id": "NY.GDP.PCAP.CD",
        "name": "GDP per capita, current US$"
      }
    ],
    "last_fetched": "2026-04-25T01:19:22.351Z"
  },
  "series": {
    "years": [
      1988, 1989, 1990, 1991, 1992, 1993, 1994, 1995, 1996, 1997, 1998, 1999, 2000, 2001, 2002,
      2003, 2004, 2005, 2006, 2007, 2008, 2009, 2010, 2011, 2012, 2013, 2014, 2015, 2016, 2017,
      2018, 2019, 2020, 2021, 2022, 2023, 2024
    ],
    "values": [
      {
        "year": 1988,
        "population": 146857000,
        "gdp_per_capita_usd": 3778.01977539063
      },
      {
        "year": 1989,
        "population": 147721000,
        "gdp_per_capita_usd": 3429.64990234375
      },
      {
        "year": 1990,
        "population": 147969406,
        "gdp_per_capita_usd": 3494.06323242188
      },
      {
        "year": 1991,
        "population": 148394216,
        "gdp_per_capita_usd": 3490.45239257813
      },
      {
        "year": 1992,
        "population": 148538197,
        "gdp_per_capita_usd": 3098.802734375
      },
      {
        "year": 1993,
        "population": 148458777,
        "gdp_per_capita_usd": 2930.67016601563
      },
      {
        "year": 1994,
        "population": 148407912,
        "gdp_per_capita_usd": 2662.10400390625
      },
      {
        "year": 1995,
        "population": 148375787,
        "gdp_per_capita_usd": 2665.77978515625
      },
      {
        "year": 1996,
        "population": 148160129,
        "gdp_per_capita_usd": 2643.92919921875
      },
      {
        "year": 1997,
        "population": 147915361,
        "gdp_per_capita_usd": 2737.57202148438
      },
      {
        "year": 1998,
        "population": 147670784,
        "gdp_per_capita_usd": 1834.86181640625
      },
      {
        "year": 1999,
        "population": 147214776,
        "gdp_per_capita_usd": 1330.75720214844
      },
      {
        "year": 2000,
        "population": 146596869,
        "gdp_per_capita_usd": 1771.59411621094
      },
      {
        "year": 2001,
        "population": 145976482,
        "gdp_per_capita_usd": 2100.3525390625
      },
      {
        "year": 2002,
        "population": 145306497,
        "gdp_per_capita_usd": 2377.52954101563
      },
      {
        "year": 2003,
        "population": 144648618,
        "gdp_per_capita_usd": 2975.123046875
      },
      {
        "year": 2004,
        "population": 144067316,
        "gdp_per_capita_usd": 4102.36474609375
      },
      {
        "year": 2005,
        "population": 143518814,
        "gdp_per_capita_usd": 5323.455078125
      },
      {
        "year": 2006,
        "population": 143049637,
        "gdp_per_capita_usd": 6920.19970703125
      },
      {
        "year": 2007,
        "population": 142805114,
        "gdp_per_capita_usd": 9101.2392578125
      },
      {
        "year": 2008,
        "population": 142742366,
        "gdp_per_capita_usd": 11635.2841796875
      },
      {
        "year": 2009,
        "population": 142785348,
        "gdp_per_capita_usd": 8562.82421875
      },
      {
        "year": 2010,
        "population": 142849468,
        "gdp_per_capita_usd": 10674.990234375
      },
      {
        "year": 2011,
        "population": 143018195,
        "gdp_per_capita_usd": 14305.33203125
      },
      {
        "year": 2012,
        "population": 143378447,
        "gdp_per_capita_usd": 15401.8515625
      },
      {
        "year": 2013,
        "population": 143805638,
        "gdp_per_capita_usd": 15941.4482421875
      },
      {
        "year": 2014,
        "population": 144237223,
        "gdp_per_capita_usd": 14055.47265625
      },
      {
        "year": 2015,
        "population": 144640716,
        "gdp_per_capita_usd": 9277.7138671875
      },
      {
        "year": 2016,
        "population": 145015460,
        "gdp_per_capita_usd": 8663.158203125
      },
      {
        "year": 2017,
        "population": 145293260,
        "gdp_per_capita_usd": 10658.9130859375
      },
      {
        "year": 2018,
        "population": 145398106,
        "gdp_per_capita_usd": 11211.8876953125
      },
      {
        "year": 2019,
        "population": 145453291,
        "gdp_per_capita_usd": 11447.701171875
      },
      {
        "year": 2020,
        "population": 145245148,
        "gdp_per_capita_usd": 10108.3271484375
      },
      {
        "year": 2021,
        "population": 144746762,
        "gdp_per_capita_usd": 12425.029296875
      },
      {
        "year": 2022,
        "population": 144236933,
        "gdp_per_capita_usd": 15619.6142578125
      },
      {
        "year": 2023,
        "population": 143826130,
        "gdp_per_capita_usd": 14159.3876953125
      },
      {
        "year": 2024,
        "population": 143533851,
        "gdp_per_capita_usd": 14889.0185546875
      }
    ]
  }
}
